pystatity/__init__.py
statity-0.0.1.dist-info/LICENSE
statity-0.0.1.dist-info/METADATA
statity-0.0.1.dist-info/WHEEL
statity-0.0.1.dist-info/top_level.txt
statity-0.0.1.dist-info/RECORD
