Metadata-Version: 2.1
Name: statity
Version: 0.0.1
Summary: Lib for checking types of functions arguments and returning data to accordance with annotating
Home-page: https://github.com/soogly/pystatity
Author: Andrey Suglobov
Author-email: sooglobov@gmail.com
License: UNKNOWN
Platform: UNKNOWN
Classifier: Programming Language :: Python :: 3
Classifier: License :: OSI Approved :: MIT License
Classifier: Operating System :: OS Independent
Requires-Python: >=3.7
